RabboniHandGes/RabboniHandGes.py
RabboniHandGes/__init__.py
RabboniHandGes/_pytransform_32.dll
RabboniHandGes/_pytransform_64.dll
RabboniHandGes/license.lic
RabboniHandGes/pytransform.key
RabboniHandGes/pytransform.py
RabboniHandGes-1.3.dist-info/METADATA
RabboniHandGes-1.3.dist-info/WHEEL
RabboniHandGes-1.3.dist-info/top_level.txt
RabboniHandGes-1.3.dist-info/RECORD
