Metadata-Version: 2.1
Name: RabboniHandGes
Version: 1.3
Summary: RabboniHandGes
Home-page: https://github.com/SuiiiDe/RabboniHandGes
Author: Sui De
Author-email: vigia22922@gmail.com
License: GNU General Public License v3.0
Platform: UNKNOWN
Requires-Dist: numpy
Requires-Dist: Pillow
